flask_structure_handler/__init__.py
flask_structure_handler/__main__.py
flask_structure_handler/flask-api-structure.zip
flask_structure-0.1.1.dist-info/LICENSE.md
flask_structure-0.1.1.dist-info/METADATA
flask_structure-0.1.1.dist-info/WHEEL
flask_structure-0.1.1.dist-info/entry_points.txt
flask_structure-0.1.1.dist-info/top_level.txt
flask_structure-0.1.1.dist-info/RECORD
