Metadata-Version: 2.1
Name: flask-structure
Version: 0.1.1
Summary: A Python library dedicated to exemplify and facilitate the start of Flask projects for APIs 💫. Download flask-structure and streamline the "start" of your projects with ease 🚀.
Author: Piedro404
Author-email: pedro.henrique.martins404@gmail.com
Project-URL: Homepage, https://github.com/piedro404/flask-structure
Project-URL: Issues, https://github.com/piedro404/flask-structure/issues
Classifier: Programming Language :: Python :: 3
Classifier: License :: OSI Approved :: MIT License
Classifier: Operating System :: OS Independent
License-File: LICENSE.md
Requires-Dist: Click
